<?xml version="1.0" encoding="utf-8" ?><dwsync><file name="mt-laptop-0.png" server="164.92.116.136//var/www/html/" local="3792848008" remote="3792848008" Dst="-1" /><file name="header-social.png" server="164.92.116.136//var/www/html/" local="3792848007" remote="3792848007" Dst="-1" /><file name="ngi-cover.png" server="164.92.116.136//var/www/html/" local="3792848009" remote="3792848009" Dst="-1" /><file name="ngi-full-2.png" server="164.92.116.136//var/www/html/" local="3792848008" remote="3792848008" Dst="-1" /><file name="ngi-hero-3.png" server="164.92.116.136//var/www/html/" local="3792848008" remote="3792848008" Dst="-1" /><file name="9.png" server="164.92.116.136//var/www/html/" local="3792848007" remote="3792848007" Dst="-1" /><file name="5.png" server="164.92.116.136//var/www/html/" local="3792848009" remote="3792848009" Dst="-1" /><file name="header-social.jpg" server="164.92.116.136//var/www/html/" local="3792848007" remote="3792848007" Dst="-1" /><file name="mt-laptop-1.png" server="164.92.116.136//var/www/html/" local="3792848008" remote="3792848008" Dst="-1" /><file name="2.png" server="164.92.116.136//var/www/html/" local="3792848009" remote="3792848009" Dst="-1" /><file name="11.png" server="164.92.116.136//var/www/html/" local="3792848007" remote="3792848007" Dst="-1" /><file name="ngi-hero-1.png" server="164.92.116.136//var/www/html/" local="3792848008" remote="3792848008" Dst="-1" /><file name="10.png" server="164.92.116.136//var/www/html/" local="3792848008" remote="3792848008" Dst="-1" /><file name="ngi-hero-2.png" server="164.92.116.136//var/www/html/" local="3792848008" remote="3792848008" Dst="-1" /><file name="mt-laptop-2.png" server="164.92.116.136//var/www/html/" local="3792848008" remote="3792848008" Dst="-1" /><file name="12.png" server="164.92.116.136//var/www/html/" local="3792848007" remote="3792848007" Dst="-1" /><file name="17.png" server="164.92.116.136//var/www/html/" local="3792848007" remote="3792848007" Dst="-1" /><file name="1.png" server="164.92.116.136//var/www/html/" local="3792848009" remote="3792848009" Dst="-1" /><file name="microtalk-hero.png" server="164.92.116.136//var/www/html/" local="3792848007" remote="3792848007" Dst="-1" /><file name="8.png" server="164.92.116.136//var/www/html/" local="3792848007" remote="3792848007" Dst="-1" /><file name="ngi-full.png" server="164.92.116.136//var/www/html/" local="3792848009" remote="3792848009" Dst="-1" /><file name="3.png" server="164.92.116.136//var/www/html/" local="3792848009" remote="3792848009" Dst="-1" /><file name="7.png" server="164.92.116.136//var/www/html/" local="3792848009" remote="3792848009" Dst="-1" /><file name="ngi-1-full.jpg" server="164.92.116.136//var/www/html/" local="3792848007" remote="3792848007" Dst="-1" /><file name="ngi-full.jpg" server="164.92.116.136//var/www/html/" local="3792848009" remote="3792848009" Dst="-1" /><file name="ngi-2-full.jpg" server="164.92.116.136//var/www/html/" local="3792848009" remote="3792848009" Dst="-1" /><file name="ms-full.jpg" server="164.92.116.136//var/www/html/" local="3792848007" remote="3792848007" Dst="-1" /><file name="microtalk-single.png" server="164.92.116.136//var/www/html/" local="3792848007" remote="3792848007" Dst="-1" /><file name="4.png" server="164.92.116.136//var/www/html/" local="3792848008" remote="3792848008" Dst="-1" /><file name="ngi-1.png" server="164.92.116.136//var/www/html/" local="3792848008" remote="3792848008" Dst="-1" /><file name="6.png" server="164.92.116.136//var/www/html/" local="3792848009" remote="3792848009" Dst="-1" /><file name="microtalk-single.png" server="137.184.87.127//var/www/html/" local="3792848007" remote="3807487747" Dst="-1" /><file name="8.png" server="137.184.87.127//var/www/html/" local="3792848007" remote="3807487747" Dst="-1" /><file name="9.png" server="137.184.87.127//var/www/html/" local="3792848007" remote="3807487748" Dst="-1" /><file name="17.png" server="137.184.87.127//var/www/html/" local="3792848007" remote="3807487748" Dst="-1" /><file name="header-social.png" server="137.184.87.127//var/www/html/" local="3792848007" remote="3807487748" Dst="-1" /><file name="header-social.jpg" server="137.184.87.127//var/www/html/" local="3792848007" remote="3807487749" Dst="-1" /><file name="12.png" server="137.184.87.127//var/www/html/" local="3792848007" remote="3807487749" Dst="-1" /><file name="microtalk-hero.png" server="137.184.87.127//var/www/html/" local="3792848007" remote="3807487750" Dst="-1" /><file name="ms-full.jpg" server="137.184.87.127//var/www/html/" local="3792848007" remote="3807487750" Dst="-1" /><file name="ngi-1-full.jpg" server="137.184.87.127//var/www/html/" local="3792848007" remote="3807487750" Dst="-1" /><file name="11.png" server="137.184.87.127//var/www/html/" local="3792848007" remote="3807487750" Dst="-1" /><file name="10.png" server="137.184.87.127//var/www/html/" local="3792848008" remote="3807487751" Dst="-1" /><file name="ngi-1.png" server="137.184.87.127//var/www/html/" local="3792848008" remote="3807487751" Dst="-1" /><file name="mt-laptop-0.png" server="137.184.87.127//var/www/html/" local="3792848008" remote="3807487751" Dst="-1" /><file name="mt-laptop-1.png" server="137.184.87.127//var/www/html/" local="3792848008" remote="3807487752" Dst="-1" /><file name="ngi-full-2.png" server="137.184.87.127//var/www/html/" local="3792848008" remote="3807487752" Dst="-1" /><file name="mt-laptop-2.png" server="137.184.87.127//var/www/html/" local="3792848008" remote="3807487752" Dst="-1" /><file name="ngi-hero-1.png" server="137.184.87.127//var/www/html/" local="3792848008" remote="3807487754" Dst="-1" /><file name="ngi-hero-3.png" server="137.184.87.127//var/www/html/" local="3792848008" remote="3807487755" Dst="-1" /><file name="ngi-hero-2.png" server="137.184.87.127//var/www/html/" local="3792848008" remote="3807487757" Dst="-1" /><file name="4.png" server="137.184.87.127//var/www/html/" local="3792848008" remote="3807487757" Dst="-1" /><file name="ngi-cover.png" server="137.184.87.127//var/www/html/" local="3792848009" remote="3807487758" Dst="-1" /><file name="5.png" server="137.184.87.127//var/www/html/" local="3792848009" remote="3807487758" Dst="-1" /><file name="ngi-full.png" server="137.184.87.127//var/www/html/" local="3792848009" remote="3807487758" Dst="-1" /><file name="ngi-full.jpg" server="137.184.87.127//var/www/html/" local="3792848009" remote="3807487758" Dst="-1" /><file name="7.png" server="137.184.87.127//var/www/html/" local="3792848009" remote="3807487759" Dst="-1" /><file name="6.png" server="137.184.87.127//var/www/html/" local="3792848009" remote="3807487759" Dst="-1" /><file name="ngi-2-full.jpg" server="137.184.87.127//var/www/html/" local="3792848009" remote="3807487759" Dst="-1" /><file name="2.png" server="137.184.87.127//var/www/html/" local="3792848009" remote="3807487760" Dst="-1" /><file name="3.png" server="137.184.87.127//var/www/html/" local="3792848009" remote="3807487760" Dst="-1" /><file name="1.png" server="137.184.87.127//var/www/html/" local="3792848009" remote="3807487761" Dst="-1" /></dwsync>